trex_id.cp311-win_amd64.pyd
trex_id-0.2.0.dist-info/LICENSE
trex_id-0.2.0.dist-info/METADATA
trex_id-0.2.0.dist-info/WHEEL
trex_id-0.2.0.dist-info/top_level.txt
trex_id-0.2.0.dist-info/RECORD
