Metadata-Version: 2.1
Name: trex_id
Version: 0.2.0
Summary: A Cython-based ID generation library using a secure and fast unique ID generation technique.
Author: Aviad Korakin
Author-email: aviad825@gmail.com
License: MIT
Classifier: Programming Language :: Python :: 3
Classifier: License :: OSI Approved :: MIT License
Classifier: Operating System :: OS Independent
Requires-Python: >=3.6
License-File: LICENSE
